instagram_text_python-2.1.0.dist-info/DESCRIPTION.rst
instagram_text_python-2.1.0.dist-info/METADATA
instagram_text_python-2.1.0.dist-info/RECORD
instagram_text_python-2.1.0.dist-info/WHEEL
instagram_text_python-2.1.0.dist-info/metadata.json
instagram_text_python-2.1.0.dist-info/top_level.txt
itp/__init__.py
itp/itp.py
itp/tests.py
itp/utils.py
