Metadata-Version: 2.0
Name: instagram-text-python
Version: 2.1.0
Summary: Instagram caption parser and formatter
Home-page: https://github.com/takumihq/instagram-text-python
Author: Maintained by Takumi (previously twitter-text-python, which is maintained by Edmond Burnett (previously Ian Ozsvald; originally Ivo Wetzel))
Author-email: itp@takumihq.com
License: MIT
Platform: UNKNOWN
Classifier: Environment :: Console
Classifier: Intended Audience :: Developers
Classifier: License :: OSI Approved :: MIT License
Classifier: Operating System :: OS Independent
Classifier: Programming Language :: Python
Classifier: Topic :: Software Development :: Libraries :: Python Modules
Classifier: Topic :: Text Processing :: Linguistic
